dinjg/__init__.py
dinjg/__main__.py
dinjg/cli.py
dinjg/core.py
dinjg/diparser.py
dinjg-0.0.2.dist-info/METADATA
dinjg-0.0.2.dist-info/WHEEL
dinjg-0.0.2.dist-info/entry_points.txt
dinjg-0.0.2.dist-info/top_level.txt
dinjg-0.0.2.dist-info/RECORD
